codi_munis_endpoints/__init__.py
codi_munis_endpoints/_munis_endpoints/_asset_management/__init__.py
codi_munis_endpoints/_munis_endpoints/_asset_management/accountbalances.py
codi_munis_endpoints/_munis_endpoints/_asset_management/accounts.py
codi_munis_endpoints/_munis_endpoints/_asset_management/accountsreceivablecodes.py
codi_munis_endpoints/_munis_endpoints/_asset_management/acquisitionmethods.py
codi_munis_endpoints/_munis_endpoints/_asset_management/applicationproject.py
codi_munis_endpoints/_munis_endpoints/_asset_management/assettypes.py
codi_munis_endpoints/_munis_endpoints/_asset_management/backflowdevices.py
codi_munis_endpoints/_munis_endpoints/_asset_management/backflowdevicetypes.py
codi_munis_endpoints/_munis_endpoints/_asset_management/bills.py
codi_munis_endpoints/_munis_endpoints/_asset_management/budgetcodes.py
codi_munis_endpoints/_munis_endpoints/_asset_management/capitalassets.py
codi_munis_endpoints/_munis_endpoints/_asset_management/chargecodes.py
codi_munis_endpoints/_munis_endpoints/_asset_management/classes.py
codi_munis_endpoints/_munis_endpoints/_asset_management/conditions.py
codi_munis_endpoints/_munis_endpoints/_asset_management/custodians.py
codi_munis_endpoints/_munis_endpoints/_asset_management/customers.py
codi_munis_endpoints/_munis_endpoints/_asset_management/departments.py
codi_munis_endpoints/_munis_endpoints/_asset_management/depreciationmethods.py
codi_munis_endpoints/_munis_endpoints/_asset_management/disposalreasons.py
codi_munis_endpoints/_munis_endpoints/_asset_management/employees.py
codi_munis_endpoints/_munis_endpoints/_asset_management/flatinventory.py
codi_munis_endpoints/_munis_endpoints/_asset_management/generalbilling.py
codi_munis_endpoints/_munis_endpoints/_asset_management/generalledgercodes.py
codi_munis_endpoints/_munis_endpoints/_asset_management/grants.py
codi_munis_endpoints/_munis_endpoints/_asset_management/invoices.py
codi_munis_endpoints/_munis_endpoints/_asset_management/items.py
codi_munis_endpoints-0.0.1.dist-info/WHEEL
codi_munis_endpoints-0.0.1.dist-info/METADATA
codi_munis_endpoints-0.0.1.dist-info/RECORD
